{
    "scryfall": {
        "object": "card",
        "id": "08c571fe-54ef-4234-98c3-5d4a7b07e7d2",
        "oracle_id": "bc891258-2f22-4248-9972-4f41905744c6",
        "multiverse_ids": [
            456734
        ],
        "mtgo_id": 70349,
        "arena_id": 83338,
        "tcgplayer_id": 180814,
        "cardmarket_id": 366853,
        "name": "Magmaw",
        "lang": "en",
        "released_at": "2018-12-07",
        "uri": "https://api.scryfall.com/cards/08c571fe-54ef-4234-98c3-5d4a7b07e7d2",
        "scryfall_uri": "https://scryfall.com/card/uma/138/magmaw?utm_source=api",
        "layout": "normal",
        "highres_image": true,
        "image_status": "highres_scan",
        "image_uris": {
            "small": "https://cards.scryfall.io/small/front/0/8/08c571fe-54ef-4234-98c3-5d4a7b07e7d2.jpg?1710406387",
            "normal": "https://cards.scryfall.io/normal/front/0/8/08c571fe-54ef-4234-98c3-5d4a7b07e7d2.jpg?1710406387",
            "large": "https://cards.scryfall.io/large/front/0/8/08c571fe-54ef-4234-98c3-5d4a7b07e7d2.jpg?1710406387",
            "png": "https://cards.scryfall.io/png/front/0/8/08c571fe-54ef-4234-98c3-5d4a7b07e7d2.png?1710406387",
            "art_crop": "https://cards.scryfall.io/art_crop/front/0/8/08c571fe-54ef-4234-98c3-5d4a7b07e7d2.jpg?1710406387",
            "border_crop": "https://cards.scryfall.io/border_crop/front/0/8/08c571fe-54ef-4234-98c3-5d4a7b07e7d2.jpg?1710406387"
        },
        "mana_cost": "{3}{R}{R}",
        "cmc": 5.0,
        "type_line": "Creature \u2014 Elemental",
        "oracle_text": "{1}, Sacrifice a nonland permanent: Magmaw deals 1 damage to any target.",
        "power": "4",
        "toughness": "4",
        "colors": [
            "R"
        ],
        "color_identity": [
            "R"
        ],
        "keywords": [],
        "legalities": {
            "standard": "not_legal",
            "future": "not_legal",
            "historic": "legal",
            "timeless": "legal",
            "gladiator": "legal",
            "pioneer": "not_legal",
            "explorer": "not_legal",
            "modern": "legal",
            "legacy": "legal",
            "pauper": "not_legal",
            "vintage": "legal",
            "penny": "legal",
            "commander": "legal",
            "oathbreaker": "legal",
            "standardbrawl": "not_legal",
            "brawl": "legal",
            "alchemy": "not_legal",
            "paupercommander": "restricted",
            "duel": "legal",
            "oldschool": "not_legal",
            "premodern": "not_legal",
            "predh": "legal"
        },
        "games": [
            "paper",
            "mtgo",
            "arena"
        ],
        "reserved": false,
        "foil": true,
        "nonfoil": true,
        "finishes": [
            "nonfoil",
            "foil"
        ],
        "oversized": false,
        "promo": false,
        "reprint": true,
        "variation": false,
        "set_id": "2ec77b94-6d47-4891-a480-5d0b4e5c9372",
        "set": "uma",
        "set_name": "Ultimate Masters",
        "set_type": "masters",
        "set_uri": "https://api.scryfall.com/sets/2ec77b94-6d47-4891-a480-5d0b4e5c9372",
        "set_search_uri": "https://api.scryfall.com/cards/search?order=set&q=e%3Auma&unique=prints",
        "scryfall_set_uri": "https://scryfall.com/sets/uma?utm_source=api",
        "rulings_uri": "https://api.scryfall.com/cards/08c571fe-54ef-4234-98c3-5d4a7b07e7d2/rulings",
        "prints_search_uri": "https://api.scryfall.com/cards/search?order=released&q=oracleid%3Abc891258-2f22-4248-9972-4f41905744c6&unique=prints",
        "collector_number": "138",
        "digital": false,
        "rarity": "uncommon",
        "flavor_text": "\"The purpose of existence is simple: everything is fuel for the magmaw.\"\n\u2014Jaji, magmaw worshipper",
        "card_back_id": "0aeebaf5-8c7d-4636-9e82-8c27447861f7",
        "artist": "Karl Kopinski",
        "artist_ids": [
            "0fad2c48-a56e-4a0b-b512-224f6f238f20"
        ],
        "illustration_id": "977987a5-f87f-4eb4-8382-e6d1a1bdbd9a",
        "border_color": "black",
        "frame": "2015",
        "full_art": false,
        "textless": false,
        "booster": true,
        "story_spotlight": false,
        "edhrec_rank": 19248,
        "prices": {
            "usd": "0.06",
            "usd_foil": "0.13",
            "usd_etched": null,
            "eur": "0.09",
            "eur_foil": "0.19",
            "tix": "0.06"
        },
        "related_uris": {
            "gatherer": "https://gatherer.wizards.com/Pages/Card/Details.aspx?multiverseid=456734&printed=false",
            "tcgplayer_infinite_articles": "https://tcgplayer.pxf.io/c/4931599/1830156/21018?subId1=api&trafcat=infinite&u=https%3A%2F%2Finfinite.tcgplayer.com%2Fsearch%3FcontentMode%3Darticle%26game%3Dmagic%26partner%3Dscryfall%26q%3DMagmaw",
            "tcgplayer_infinite_decks": "https://tcgplayer.pxf.io/c/4931599/1830156/21018?subId1=api&trafcat=infinite&u=https%3A%2F%2Finfinite.tcgplayer.com%2Fsearch%3FcontentMode%3Ddeck%26game%3Dmagic%26partner%3Dscryfall%26q%3DMagmaw",
            "edhrec": "https://edhrec.com/route/?cc=Magmaw"
        },
        "purchase_uris": {
            "tcgplayer": "https://tcgplayer.pxf.io/c/4931599/1830156/21018?subId1=api&u=https%3A%2F%2Fwww.tcgplayer.com%2Fproduct%2F180814%3Fpage%3D1",
            "cardmarket": "https://www.cardmarket.com/en/Magic/Products/Singles/Ultimate-Masters/Magmaw?referrer=scryfall&utm_campaign=card_prices&utm_medium=text&utm_source=scryfall",
            "cardhoarder": "https://www.cardhoarder.com/cards/70349?affiliate_id=scryfall&ref=card-profile&utm_campaign=affiliate&utm_medium=card&utm_source=scryfall"
        }
    },
    "count": 1,
    "17lands": {}
}