{
    "scryfall": {
        "object": "card",
        "id": "17a104d3-e4ac-44a0-9c6a-39965b1b9751",
        "oracle_id": "510659d6-69b4-4b04-8836-08b76213954e",
        "multiverse_ids": [
            655100
        ],
        "mtgo_id": 124229,
        "arena_id": 90505,
        "tcgplayer_id": 544223,
        "cardmarket_id": 763572,
        "name": "Colossal Rattlewurm",
        "lang": "en",
        "released_at": "2024-04-19",
        "uri": "https://api.scryfall.com/cards/17a104d3-e4ac-44a0-9c6a-39965b1b9751",
        "scryfall_uri": "https://scryfall.com/card/otj/159/colossal-rattlewurm?utm_source=api",
        "layout": "normal",
        "highres_image": true,
        "image_status": "highres_scan",
        "image_uris": {
            "small": "https://cards.scryfall.io/small/front/1/7/17a104d3-e4ac-44a0-9c6a-39965b1b9751.jpg?1712355903",
            "normal": "https://cards.scryfall.io/normal/front/1/7/17a104d3-e4ac-44a0-9c6a-39965b1b9751.jpg?1712355903",
            "large": "https://cards.scryfall.io/large/front/1/7/17a104d3-e4ac-44a0-9c6a-39965b1b9751.jpg?1712355903",
            "png": "https://cards.scryfall.io/png/front/1/7/17a104d3-e4ac-44a0-9c6a-39965b1b9751.png?1712355903",
            "art_crop": "https://cards.scryfall.io/art_crop/front/1/7/17a104d3-e4ac-44a0-9c6a-39965b1b9751.jpg?1712355903",
            "border_crop": "https://cards.scryfall.io/border_crop/front/1/7/17a104d3-e4ac-44a0-9c6a-39965b1b9751.jpg?1712355903"
        },
        "mana_cost": "{2}{G}{G}",
        "cmc": 4.0,
        "type_line": "Creature \u2014 Wurm",
        "oracle_text": "Colossal Rattlewurm has flash as long as you control a Desert.\nTrample\n{1}{G}, Exile Colossal Rattlewurm from your graveyard: Search your library for a Desert card, put it onto the battlefield tapped, then shuffle.",
        "power": "6",
        "toughness": "5",
        "colors": [
            "G"
        ],
        "color_identity": [
            "G"
        ],
        "keywords": [
            "Trample"
        ],
        "legalities": {
            "standard": "legal",
            "future": "legal",
            "historic": "legal",
            "timeless": "legal",
            "gladiator": "legal",
            "pioneer": "legal",
            "explorer": "legal",
            "modern": "legal",
            "legacy": "legal",
            "pauper": "not_legal",
            "vintage": "legal",
            "penny": "not_legal",
            "commander": "legal",
            "oathbreaker": "legal",
            "standardbrawl": "legal",
            "brawl": "legal",
            "alchemy": "legal",
            "paupercommander": "not_legal",
            "duel": "legal",
            "oldschool": "not_legal",
            "premodern": "not_legal",
            "predh": "not_legal"
        },
        "games": [
            "paper",
            "mtgo",
            "arena"
        ],
        "reserved": false,
        "foil": true,
        "nonfoil": true,
        "finishes": [
            "nonfoil",
            "foil"
        ],
        "oversized": false,
        "promo": false,
        "reprint": false,
        "variation": false,
        "set_id": "55a85ebe-644e-4bef-8be8-5290408be3d1",
        "set": "otj",
        "set_name": "Outlaws of Thunder Junction",
        "set_type": "expansion",
        "set_uri": "https://api.scryfall.com/sets/55a85ebe-644e-4bef-8be8-5290408be3d1",
        "set_search_uri": "https://api.scryfall.com/cards/search?order=set&q=e%3Aotj&unique=prints",
        "scryfall_set_uri": "https://scryfall.com/sets/otj?utm_source=api",
        "rulings_uri": "https://api.scryfall.com/cards/17a104d3-e4ac-44a0-9c6a-39965b1b9751/rulings",
        "prints_search_uri": "https://api.scryfall.com/cards/search?order=released&q=oracleid%3A510659d6-69b4-4b04-8836-08b76213954e&unique=prints",
        "collector_number": "159",
        "digital": false,
        "rarity": "rare",
        "card_back_id": "0aeebaf5-8c7d-4636-9e82-8c27447861f7",
        "artist": "Filip Burburan",
        "artist_ids": [
            "66082c3b-a623-4d34-be51-2475214b85d3"
        ],
        "illustration_id": "4a35e3b5-1ab5-4192-8717-9d5a759f3f45",
        "border_color": "black",
        "frame": "2015",
        "security_stamp": "oval",
        "full_art": false,
        "textless": false,
        "booster": true,
        "story_spotlight": false,
        "edhrec_rank": 14887,
        "prices": {
            "usd": "0.55",
            "usd_foil": "0.52",
            "usd_etched": null,
            "eur": "0.29",
            "eur_foil": "0.59",
            "tix": "0.01"
        },
        "related_uris": {
            "gatherer": "https://gatherer.wizards.com/Pages/Card/Details.aspx?multiverseid=655100&printed=false",
            "tcgplayer_infinite_articles": "https://tcgplayer.pxf.io/c/4931599/1830156/21018?subId1=api&trafcat=infinite&u=https%3A%2F%2Finfinite.tcgplayer.com%2Fsearch%3FcontentMode%3Darticle%26game%3Dmagic%26partner%3Dscryfall%26q%3DColossal%2BRattlewurm",
            "tcgplayer_infinite_decks": "https://tcgplayer.pxf.io/c/4931599/1830156/21018?subId1=api&trafcat=infinite&u=https%3A%2F%2Finfinite.tcgplayer.com%2Fsearch%3FcontentMode%3Ddeck%26game%3Dmagic%26partner%3Dscryfall%26q%3DColossal%2BRattlewurm",
            "edhrec": "https://edhrec.com/route/?cc=Colossal+Rattlewurm"
        },
        "purchase_uris": {
            "tcgplayer": "https://tcgplayer.pxf.io/c/4931599/1830156/21018?subId1=api&u=https%3A%2F%2Fwww.tcgplayer.com%2Fproduct%2F544223%3Fpage%3D1",
            "cardmarket": "https://www.cardmarket.com/en/Magic/Products/Singles/Outlaws-of-Thunder-Junction/Colossal-Rattlewurm?referrer=scryfall&utm_campaign=card_prices&utm_medium=text&utm_source=scryfall",
            "cardhoarder": "https://www.cardhoarder.com/cards/124229?affiliate_id=scryfall&ref=card-profile&utm_campaign=affiliate&utm_medium=card&utm_source=scryfall"
        }
    },
    "count": 1,
    "17lands": {
        "# Seen": 8937,
        "ALSA": 1.5,
        "# Picked": 6617,
        "ATA": 1.5,
        "# GP": 38404,
        "% GP": 94.7,
        "GP WR": 56.9,
        "# OH": 6637,
        "OH WR": 60.6,
        "# GD": 9077,
        "GD WR": 61.2,
        "# GIH": 15714,
        "GIH WR": 61.0,
        "# GNS": 22508,
        "GNS WR": 53.9,
        "IWD": 7.1
    }
}