{
    "scryfall": {
        "object": "card",
        "id": "158c000e-7960-4518-b034-a529622b7bf1",
        "oracle_id": "de83b1a4-0ce0-4cc1-aff3-6d0239d92302",
        "multiverse_ids": [
            660306
        ],
        "mtgo_id": 125381,
        "arena_id": 90671,
        "tcgplayer_id": 545123,
        "name": "Hostile Investigator",
        "lang": "en",
        "released_at": "2024-04-19",
        "uri": "https://api.scryfall.com/cards/158c000e-7960-4518-b034-a529622b7bf1",
        "scryfall_uri": "https://scryfall.com/card/big/10/hostile-investigator?utm_source=api",
        "layout": "normal",
        "highres_image": true,
        "image_status": "highres_scan",
        "image_uris": {
            "small": "https://cards.scryfall.io/small/front/1/5/158c000e-7960-4518-b034-a529622b7bf1.jpg?1712352777",
            "normal": "https://cards.scryfall.io/normal/front/1/5/158c000e-7960-4518-b034-a529622b7bf1.jpg?1712352777",
            "large": "https://cards.scryfall.io/large/front/1/5/158c000e-7960-4518-b034-a529622b7bf1.jpg?1712352777",
            "png": "https://cards.scryfall.io/png/front/1/5/158c000e-7960-4518-b034-a529622b7bf1.png?1712352777",
            "art_crop": "https://cards.scryfall.io/art_crop/front/1/5/158c000e-7960-4518-b034-a529622b7bf1.jpg?1712352777",
            "border_crop": "https://cards.scryfall.io/border_crop/front/1/5/158c000e-7960-4518-b034-a529622b7bf1.jpg?1712352777"
        },
        "mana_cost": "{3}{B}",
        "cmc": 4.0,
        "type_line": "Creature \u2014 Ogre Rogue Detective",
        "oracle_text": "When Hostile Investigator enters the battlefield, target opponent discards a card.\nWhenever one or more players discard one or more cards, investigate. This ability triggers only once each turn. (Create a Clue token. It's an artifact with \"{2}, Sacrifice this artifact: Draw a card.\")",
        "power": "4",
        "toughness": "3",
        "colors": [
            "B"
        ],
        "color_identity": [
            "B"
        ],
        "keywords": [
            "Investigate"
        ],
        "all_parts": [
            {
                "object": "related_card",
                "id": "764a906c-8b27-4ffa-bdc3-7825c6919d3e",
                "component": "token",
                "name": "Clue",
                "type_line": "Token Artifact \u2014 Clue",
                "uri": "https://api.scryfall.com/cards/764a906c-8b27-4ffa-bdc3-7825c6919d3e"
            },
            {
                "object": "related_card",
                "id": "0a3c9365-af51-4874-be5b-57d0514825fe",
                "component": "combo_piece",
                "name": "Hostile Investigator",
                "type_line": "Creature \u2014 Ogre Rogue Detective",
                "uri": "https://api.scryfall.com/cards/0a3c9365-af51-4874-be5b-57d0514825fe"
            }
        ],
        "legalities": {
            "standard": "legal",
            "future": "legal",
            "historic": "legal",
            "timeless": "legal",
            "gladiator": "legal",
            "pioneer": "legal",
            "explorer": "legal",
            "modern": "legal",
            "legacy": "legal",
            "pauper": "not_legal",
            "vintage": "legal",
            "penny": "not_legal",
            "commander": "legal",
            "oathbreaker": "legal",
            "standardbrawl": "legal",
            "brawl": "legal",
            "alchemy": "legal",
            "paupercommander": "not_legal",
            "duel": "legal",
            "oldschool": "not_legal",
            "premodern": "not_legal",
            "predh": "not_legal"
        },
        "games": [
            "paper",
            "arena",
            "mtgo"
        ],
        "reserved": false,
        "foil": true,
        "nonfoil": true,
        "finishes": [
            "nonfoil",
            "foil"
        ],
        "oversized": false,
        "promo": false,
        "reprint": false,
        "variation": false,
        "set_id": "14332d2c-ba93-4498-bf3f-9d601f88f783",
        "set": "big",
        "set_name": "The Big Score",
        "set_type": "expansion",
        "set_uri": "https://api.scryfall.com/sets/14332d2c-ba93-4498-bf3f-9d601f88f783",
        "set_search_uri": "https://api.scryfall.com/cards/search?order=set&q=e%3Abig&unique=prints",
        "scryfall_set_uri": "https://scryfall.com/sets/big?utm_source=api",
        "rulings_uri": "https://api.scryfall.com/cards/158c000e-7960-4518-b034-a529622b7bf1/rulings",
        "prints_search_uri": "https://api.scryfall.com/cards/search?order=released&q=oracleid%3Ade83b1a4-0ce0-4cc1-aff3-6d0239d92302&unique=prints",
        "collector_number": "10",
        "digital": false,
        "rarity": "mythic",
        "card_back_id": "0aeebaf5-8c7d-4636-9e82-8c27447861f7",
        "artist": "Andrew Mar",
        "artist_ids": [
            "adad79bf-cd52-456a-b170-740ed8bff0fc"
        ],
        "illustration_id": "6e67e847-984c-4c5d-aca7-3f6c4c0877d5",
        "border_color": "black",
        "frame": "2015",
        "security_stamp": "oval",
        "full_art": false,
        "textless": false,
        "booster": false,
        "story_spotlight": false,
        "promo_types": [
            "boosterfun"
        ],
        "edhrec_rank": 21614,
        "preview": {
            "source": "Gamerbraves",
            "source_uri": "https://www.gamerbraves.com/mtg-outlaws-of-thunder-junction-hostile-investigator-generates-card-draw-through-clue-tokens-and-discards/",
            "previewed_at": "2024-04-03"
        },
        "prices": {
            "usd": "1.78",
            "usd_foil": "1.71",
            "usd_etched": null,
            "eur": null,
            "eur_foil": null,
            "tix": "2.85"
        },
        "related_uris": {
            "gatherer": "https://gatherer.wizards.com/Pages/Card/Details.aspx?multiverseid=660306&printed=false",
            "tcgplayer_infinite_articles": "https://tcgplayer.pxf.io/c/4931599/1830156/21018?subId1=api&trafcat=infinite&u=https%3A%2F%2Finfinite.tcgplayer.com%2Fsearch%3FcontentMode%3Darticle%26game%3Dmagic%26partner%3Dscryfall%26q%3DHostile%2BInvestigator",
            "tcgplayer_infinite_decks": "https://tcgplayer.pxf.io/c/4931599/1830156/21018?subId1=api&trafcat=infinite&u=https%3A%2F%2Finfinite.tcgplayer.com%2Fsearch%3FcontentMode%3Ddeck%26game%3Dmagic%26partner%3Dscryfall%26q%3DHostile%2BInvestigator",
            "edhrec": "https://edhrec.com/route/?cc=Hostile+Investigator"
        },
        "purchase_uris": {
            "tcgplayer": "https://tcgplayer.pxf.io/c/4931599/1830156/21018?subId1=api&u=https%3A%2F%2Fwww.tcgplayer.com%2Fproduct%2F545123%3Fpage%3D1",
            "cardmarket": "https://www.cardmarket.com/en/Magic/Products/Search?referrer=scryfall&searchString=Hostile+Investigator&utm_campaign=card_prices&utm_medium=text&utm_source=scryfall",
            "cardhoarder": "https://www.cardhoarder.com/cards/125381?affiliate_id=scryfall&ref=card-profile&utm_campaign=affiliate&utm_medium=card&utm_source=scryfall"
        }
    },
    "count": 1,
    "17lands": {
        "# Seen": 3748,
        "ALSA": 1.67,
        "# Picked": 2458,
        "ATA": 1.71,
        "# GP": 14210,
        "% GP": 93.7,
        "GP WR": 57.5,
        "# OH": 2564,
        "OH WR": 62.9,
        "# GD": 3579,
        "GD WR": 62.3,
        "# GIH": 6143,
        "GIH WR": 62.5,
        "# GNS": 7941,
        "GNS WR": 53.4,
        "IWD": 9.1
    }
}